{
  "indexes": [
    {
      "collectionGroup": "users",
      "queryScope": "COLLECTION",
      "fields": [
        { "fieldPath": "totalScore", "order": "DESCENDING" },
        { "fieldPath": "perfectScores", "order": "DESCENDING" },
        { "fieldPath": "quizzesPlayed", "order": "ASCENDING" },
        { "fieldPath": "name", "order": "ASCENDING" }
      ]
    },
    {
      "collectionGroup": "users",
      "queryScope": "COLLECTION",
      "fields": [
        { "fieldPath": "currentStreak", "order": "DESCENDING" },
        { "fieldPath": "name", "order": "ASCENDING" }
      ]
    },
    {
      "collectionGroup": "entries",
      "queryScope": "COLLECTION",
      "fields": [
        { "fieldPath": "score", "order": "DESCENDING" },
        { "fieldPath": "time", "order": "ASCENDING" }
      ]
    },
    {
      "collectionGroup": "quizAttempts",
      "queryScope": "COLLECTION",
      "fields": [
        { "fieldPath": "timestamp", "order": "DESCENDING" }
      ]
    },
    {
      "collectionGroup": "userContributions",
      "queryScope": "COLLECTION",
      "fields": [
        { "fieldPath": "userId", "order": "ASCENDING" },
        { "fieldPath": "submittedAt", "order": "DESCENDING" }
      ]
    },
    {
      "collectionGroup": "payouts",
      "queryScope": "COLLECTION",
      "fields": [
        { "fieldPath": "status", "order": "ASCENDING" },
        { "fieldPath": "createdAt", "order": "DESCENDING" }
      ]
    },
    {
      "collectionGroup": "users",
      "queryScope": "COLLECTION",
      "fields": [
        { "fieldPath": "name", "order": "ASCENDING" }
      ]
    }
  ],
  "fieldOverrides": []
}
